history_matching/__init__.py
history_matching/emulator/__init__.py
history_matching/emulator/emulator.py
history_matching/emulator/gp_emulator.py
history_matching/emulator/implausibility.py
history_matching/samples/__init__.py
history_matching/samples/sample_space.py
history_matching/samples/stats.py
history_matching-0.1.1.dist-info/LICENSE
history_matching-0.1.1.dist-info/METADATA
history_matching-0.1.1.dist-info/WHEEL
history_matching-0.1.1.dist-info/top_level.txt
history_matching-0.1.1.dist-info/RECORD
