Metadata-Version: 2.1
Name: history_matching
Version: 0.1.1
Summary: Package contains helper modules for using history matching for parameter optimzation.
Author-email: Robert King <robcking@stanford.edu>
Project-URL: Homepage, https://github.com/OneOneFour/History-Matching-Core
Classifier: Programming Language :: Python :: 3
Classifier: License :: OSI Approved :: GNU General Public License v3 (GPLv3)
Classifier: Operating System :: OS Independent
Requires-Python: >=3.8
License-File: LICENSE
Requires-Dist: netcdf4 >=1.6.2
Requires-Dist: xarray >=2023.2.0
Requires-Dist: joblib >=1.2.0
Requires-Dist: numpy >=1.24.2
Requires-Dist: pyDOE >=0.3.8
Requires-Dist: scikit-learn >=1.2.1
Requires-Dist: scipy >=1.10.0
